.coveragerc
.pylintrc
LICENSE
MANIFEST.in
Makefile
README.md
setup.py
test.py
test_drivers.cfg
docs/technical-overview.md
gauged/__init__.py
gauged/aggregates.py
gauged/bridge.py
gauged/config.py
gauged/context.py
gauged/gauged.py
gauged/lru.py
gauged/utilities.py
gauged/version.py
gauged/writer.py
gauged.egg-info/PKG-INFO
gauged.egg-info/SOURCES.txt
gauged.egg-info/dependency_links.txt
gauged.egg-info/top_level.txt
gauged/drivers/__init__.py
gauged/drivers/interface.py
gauged/drivers/mysql.py
gauged/drivers/postgresql.py
gauged/drivers/sqlite.py
gauged/errors/__init__.py
gauged/results/__init__.py
gauged/results/statistics.py
gauged/results/time_series.py
gauged/structures/__init__.py
gauged/structures/float_array.py
gauged/structures/sparse_map.py
include/array.h
include/common.h
include/hash.h
include/map.h
include/sort.h
include/writer.h
lib/array.c
lib/hash.c
lib/map.c
lib/sort.c
lib/writer.c
test/__init__.py
test/benchmark.c
test/ctest.h
test/test.c
test/test.h
test/test_case.py
test/test_driver.py
test/test_dsn.py
test/test_gauged.py
test/test_lru.py
test/test_result.py
test/test_structures.py