Metadata-Version: 1.0
Name: gauged
Version: 0.1.0
Summary: A fast, append-only storage layer for numeric data that changes over time
Home-page: https://github.com/chriso/gauged
Author: Chris O'Hara
Author-email: cohara87@gmail.com
License: GPL
Platform: UNKNOWN
